MANIFEST.in
README.txt
sc-releaser.cfg
setup.cfg
setup.py
Products/__init__.py
Products.CMFPublicator.egg-info/PKG-INFO
Products.CMFPublicator.egg-info/SOURCES.txt
Products.CMFPublicator.egg-info/dependency_links.txt
Products.CMFPublicator.egg-info/entry_points.txt
Products.CMFPublicator.egg-info/namespace_packages.txt
Products.CMFPublicator.egg-info/not-zip-safe
Products.CMFPublicator.egg-info/requires.txt
Products.CMFPublicator.egg-info/top_level.txt
Products/CMFPublicator/PublicationBoxInformation.py
Products/CMFPublicator/PublicatorTool.py
Products/CMFPublicator/README.txt
Products/CMFPublicator/__init__.py
Products/CMFPublicator/config.py
Products/CMFPublicator/configure.zcml
Products/CMFPublicator/interfaces.py
Products/CMFPublicator/setuphandlers.py
Products/CMFPublicator/skins.zcml
Products/CMFPublicator/tests.py
Products/CMFPublicator/version.txt
Products/CMFPublicator/browser/__init__.py
Products/CMFPublicator/browser/configure.zcml
Products/CMFPublicator/browser/publicator_portlet.pt
Products/CMFPublicator/browser/publicator_portlet.py
Products/CMFPublicator/doc/AUTHORS.txt
Products/CMFPublicator/doc/CHANGES.txt
Products/CMFPublicator/doc/CREDITS.txt
Products/CMFPublicator/doc/DEPENDENCIES.txt
Products/CMFPublicator/doc/HISTORY.txt
Products/CMFPublicator/doc/LICENSE.txt
Products/CMFPublicator/doc/TODO.txt
Products/CMFPublicator/help/CMFPublicator_Configuration.stx
Products/CMFPublicator/help/CMFPublicator_Example.stx
Products/CMFPublicator/help/CMFPublicator_SpecialUses.stx
Products/CMFPublicator/help/CMFPublicator_StoredItems.stx
Products/CMFPublicator/i18n/Products.CMFPublicator.pot
Products/CMFPublicator/i18n/manual.pot
Products/CMFPublicator/i18n/rebuildAll.sh
Products/CMFPublicator/i18n/pt_BR/LC_MESSAGES/Products.CMFPublicator.mo
Products/CMFPublicator/i18n/pt_BR/LC_MESSAGES/Products.CMFPublicator.po
Products/CMFPublicator/profiles/default/Products.CMFPublicator.txt
Products/CMFPublicator/profiles/default/actions.xml
Products/CMFPublicator/profiles/default/import_steps.xml
Products/CMFPublicator/profiles/default/metadata.xml
Products/CMFPublicator/profiles/default/portlets.xml
Products/CMFPublicator/profiles/default/skins.xml
Products/CMFPublicator/profiles/default/toolset.xml
Products/CMFPublicator/profiles/default/types.xml
Products/CMFPublicator/skins/publicator/getPublicatorItemInfo.py
