Metadata-Version: 1.0
Name: Products.CMFPublicator
Version: 1.3.1
Summary: CMFPublicator provides a METAL mechanism to publish contents in an arbitrary order, inside classic portlets or home boxes.
Home-page: http://svn.plone.org/svn/collective/Products.CMFPublicator
Author: Jean Ferri
Author-email: jeanrodrigoferri@yahoo.com.br
License: GPL
Keywords: layout content editorial selection publicator
Platform: UNKNOWN
Classifier: Framework :: Plone
Classifier: Framework :: Zope2
Classifier: Framework :: Zope3
Classifier: Programming Language :: Python
Classifier: Topic :: Software Development :: Libraries :: Python Modules
